[
    {
        "name": "Centro Federal de Educação Tecnológina",
        "disciplinas":[],
        "turmas":[
            {
                "nome": "ELT C",
                "ano":2015,
                "alunos":[{
                    "nome": "Gabriel Arthur",
                    "idade": 17,
                    "notas": {
                        "enem":{
                            "LINGUAGENS":0.0,
                            "EXATAS":0.0,
                            "HUMANAS":0.0,
                            "NATUREZA":0.0
                        },
                        "historico_escolar":[]
                    }
                }]
            }
        ]
    }
    
]